[
  {
    "judul": "Sosialisasi Keselamatan Berkendara bersama Dinas Perhubungan Kab. Sidoarjo",
    "tanggal": "15 April 2026",
    "ringkasan": "Dishub Sidoarjo sosialisasikan keselamatan berkendara kepada siswa.",
    "kontenLengkap": "<p>Kegiatan sosialisasi keselamatan berkendara bersama Dinas Perhubungan Kabupaten Sidoarjo dilaksanakan pada 15 April 2026. Kegiatan ini bertujuan meningkatkan kesadaran siswa akan pentingnya tertib berlalu lintas.</p><p>Dalam kegiatan tersebut, peserta mendapatkan materi terkait aturan berkendara, etika di jalan, serta pentingnya penggunaan perlengkapan keselamatan. Diharapkan siswa dapat menjadi pelopor keselamatan berlalu lintas di lingkungan masyarakat.</p>",
    "gambar": "https://res.cloudinary.com/dkfcuwuas/image/upload/v1776437100/_DSC5253_amajdc.jpg"
  }
]